{
    "type": "MyACG搜索源",
    "name": "动漫类",
    "summary": "一些动漫搜索源",
    "sources": "https://gitee.com/yx_myacg/ACGSourceRepository/raw/master/sources/",
    "author": "雨夏",
    "versionName": "1.0",
    "versionCode": 1,
    "list": [
        {
            "name": "AGE动漫",
            "summary": "https://www.agefans.tv",
            "checked": true,
            "category": 3
        },
        {
            "name": "风车动漫",
            "summary": "http://dm.dm530.net",
            "checked": true,
            "category": 3
        },
        {
            "name": "嘀哩嘀哩",
            "summary": "http://www.dilidili.one",
            "checked": true,
            "category": 3
        },
        {
            "name": "奇奇动漫",
            "summary": "http://m.qiqidongman.com",
            "checked": true,
            "category": 3
        },
        {
            "name": "妮可动漫",
            "summary": "http://www.nicotv.me",
            "checked": true,
            "category": 3
        },
        {
            "name": "乐天动漫",
            "summary": "http://www.tldm.net",
            "checked": true,
            "category": 3
        },
        {
            "name": "哔咪哔咪",
            "summary": "http://www.bimibimi.tv",
            "checked": true,
            "category": 3
        }
    ]
}