{
  "name": "动漫西西",
  "introduction": "可以搜索一些网盘资源",
  "developer": "雨夏",
  "mail":"2534246654@qq.com",
  "versionName": "1.0",
  "versionCode": 1,
  "tab":"百度云",
  "request": "http://www.dmxixi.com/plus/search.php?keyword=[$key]&PageNo=[$page]@charset->UTF-8",
  "search": {
    "list": "function Main(html){return jsoups(html,'#listvod > ul > li');}",
    "title": "function Main(text){return jsoup(text,'div > h2 > a');}",
    "introduction": "function Main(text){return jsoup(text,'div > p');}",
    "cover": "function Main(text){return jsoup(text,'a > img@attr->data-original');}",
    "url": "function Main(text){return jsoup(text,'div > h2 > a@attr->href');}"
  }
}